{"config": {"view": {"continuousWidth": 300, "continuousHeight": 300, "strokeWidth": 0}, "title": {"dx": 60, "dy": -15, "fontSize": 15}}, "data": {"name": "data-9fe553072766c6447fe70bad9ba2977d"}, "mark": {"type": "bar"}, "encoding": {"color": {"field": "cat", "legend": {"labelFontSize": 12, "symbolSize": 400}, "scale": {"domain": ["1", "2", "3", "4", "5"], "reverse": true, "scheme": "spectral"}, "title": null, "type": "nominal"}, "column": {"field": "seg2", "header": {"labelFontSize": 15}, "sort": {"field": "order"}, "title": null, "type": "nominal"}, "order": {"field": "order", "sort": "descending", "type": "quantitative"}, "row": {"field": "seg1", "header": {"labelFontSize": 15}, "sort": {"field": "order"}, "title": null, "type": "nominal"}, "tooltip": [{"field": "cat", "title": "Valor", "type": "nominal"}, {"field": "prop", "format": ".2%", "title": "Estimaci\u00f3n", "type": "quantitative"}, {"field": "lower", "format": ".2%", "title": "L\u00edmite inferior", "type": "quantitative"}, {"field": "upper", "format": ".2%", "title": "L\u00edmite superior", "type": "quantitative"}], "x": {"axis": {"labelAngle": 0, "labelFontSize": 11}, "field": "M", "sort": {"field": "order"}, "title": null, "type": "nominal"}, "y": {"axis": {"format": "%", "labelFontSize": 11}, "field": "prop", "scale": {"nice": false}, "title": null, "type": "quantitative"}}, "height": 175, "params": [{"name": "param_1304", "select": {"type": "point", "fields": ["cat"], "on": "click", "toggle": "true"}, "bind": "legend"}, {"name": "param_1305", "select": {"type": "interval", "encodings": ["x", "y"]}, "bind": "scales"}], "resolve": {"axis": {"x": "independent", "y": "independent"}}, "title": {"text": ["Poblaci\u00f3n seg\u00fan frecuencia (de 1= nunca a 5= con mucha frecuencia)  con incremento de la tensi\u00f3n arterial en cada medici\u00f3n seg\u00fan sexo y", "nivel de estudios (porcentajes e intervalos de confianza al 95%)"], "subtitle": "Fuente: Encuesta Sanitaria y Social de Andaluc\u00eda. C\u00f3digo de variable: P24_3"}, "transform": [{"filter": {"param": "param_1304"}}, {"filter": "indexof(datum.M, 'M') != -1"}], "width": 175, "$schema": "https://vega.github.io/schema/vega-lite/v5.8.0.json", "datasets": {"data-9fe553072766c6447fe70bad9ba2977d": [{"M": "M1", "seg1": "Hombre", "seg2": "Hasta primaria", "cat": "1", "prop": 0.8741733743477422, "lower": 0.8323587854458808, "upper": 0.9124286930693326, "order": 0}, {"M": "M1", "seg1": "Hombre", "seg2": "Hasta primaria", "cat": "2", "prop": 0.03456586373339759, "lower": 0.017249072300841085, "upper": 0.06479329422301337, "order": 1}, {"M": "M1", "seg1": "Hombre", "seg2": "Hasta primaria", "cat": "3", "prop": 0.05651928369896409, "lower": 0.032800010786284715, "upper": 0.09100544806925358, "order": 2}, {"M": "M1", "seg1": "Hombre", "seg2": "Hasta primaria", "cat": "4", "prop": 0.013665262159456444, "lower": 0.003398038987068704, "upper": 0.03278330227858332, "order": 3}, {"M": "M1", "seg1": "Hombre", "seg2": "Hasta primaria", "cat": "5", "prop": 0.021076216060439575, "lower": 0.007860767687263728, "upper": 0.044201979919038036, "order": 4}, {"M": "M1", "seg1": "Hombre", "seg2": "Secundaria o FP grado sup", "cat": "1", "prop": 0.893397657939346, "lower": 0.8675257435878337, "upper": 0.9163368284195328, "order": 5}, {"M": "M1", "seg1": "Hombre", "seg2": "Secundaria o FP grado sup", "cat": "2", "prop": 0.035615812761054, "lower": 0.024195494150049155, "upper": 0.05298922879912095, "order": 6}, {"M": "M1", "seg1": "Hombre", "seg2": "Secundaria o FP grado sup", "cat": "3", "prop": 0.036343453927079675, "lower": 0.02327713208894253, "upper": 0.05102304782859906, "order": 7}, {"M": "M1", "seg1": "Hombre", "seg2": "Secundaria o FP grado sup", "cat": "4", "prop": 0.01952156474083786, "lower": 0.010808478747965177, "upper": 0.032220061482979435, "order": 8}, {"M": "M1", "seg1": "Hombre", "seg2": "Secundaria o FP grado sup", "cat": "5", "prop": 0.015121510631682444, "lower": 0.007008613326387459, "upper": 0.029840389816669765, "order": 9}, {"M": "M1", "seg1": "Hombre", "seg2": "Estudios universitarios o m\u00e1s", "cat": "1", "prop": 0.8629991733652734, "lower": 0.8171975350426768, "upper": 0.8976052710386867, "order": 10}, {"M": "M1", "seg1": "Hombre", "seg2": "Estudios universitarios o m\u00e1s", "cat": "2", "prop": 0.06881677047188463, "lower": 0.046881737294547435, "upper": 0.0963832024348555, "order": 11}, {"M": "M1", "seg1": "Hombre", "seg2": "Estudios universitarios o m\u00e1s", "cat": "3", "prop": 0.034404004141370806, "lower": 0.019550272564189675, "upper": 0.05376289733009842, "order": 12}, {"M": "M1", "seg1": "Hombre", "seg2": "Estudios universitarios o m\u00e1s", "cat": "4", "prop": 0.013377857380140298, "lower": 0.004674009038493774, "upper": 0.029143536996511014, "order": 13}, {"M": "M1", "seg1": "Hombre", "seg2": "Estudios universitarios o m\u00e1s", "cat": "5", "prop": 0.020402194641330855, "lower": 0.00406122638232497, "upper": 0.07893338304483945, "order": 14}, {"M": "M1", "seg1": "Hombre", "seg2": "Total", "cat": "1", "prop": 0.880765221223547, "lower": 0.8612880032095078, "upper": 0.8982104902895073, "order": 15}, {"M": "M1", "seg1": "Hombre", "seg2": "Total", "cat": "2", "prop": 0.04533746178771366, "lower": 0.03570285205589074, "upper": 0.05771596531733136, "order": 16}, {"M": "M1", "seg1": "Hombre", "seg2": "Total", "cat": "3", "prop": 0.03949380041950723, "lower": 0.030713427041655875, "upper": 0.05092097989536953, "order": 17}, {"M": "M1", "seg1": "Hombre", "seg2": "Total", "cat": "4", "prop": 0.016604136731431213, "lower": 0.010888431640348929, "upper": 0.023881889406826028, "order": 18}, {"M": "M1", "seg1": "Hombre", "seg2": "Total", "cat": "5", "prop": 0.017799379837800815, "lower": 0.010649663129908346, "upper": 0.03535182691674633, "order": 19}, {"M": "M1", "seg1": "Mujer", "seg2": "Hasta primaria", "cat": "1", "prop": 0.7893000327506082, "lower": 0.7474394019640132, "upper": 0.8311857497789461, "order": 20}, {"M": "M1", "seg1": "Mujer", "seg2": "Hasta primaria", "cat": "2", "prop": 0.05563362250973109, "lower": 0.034936148015440975, "upper": 0.08574030169850339, "order": 21}, {"M": "M1", "seg1": "Mujer", "seg2": "Hasta primaria", "cat": "3", "prop": 0.059042924753283356, "lower": 0.03630639792490652, "upper": 0.0838187086809999, "order": 22}, {"M": "M1", "seg1": "Mujer", "seg2": "Hasta primaria", "cat": "4", "prop": 0.035473087135488544, "lower": 0.01795367702490997, "upper": 0.05768804702594198, "order": 23}, {"M": "M1", "seg1": "Mujer", "seg2": "Hasta primaria", "cat": "5", "prop": 0.06055033285088868, "lower": 0.039012771356257296, "upper": 0.08952297173503757, "order": 24}, {"M": "M1", "seg1": "Mujer", "seg2": "Secundaria o FP grado sup", "cat": "1", "prop": 0.8390149989525716, "lower": 0.8082785005113999, "upper": 0.8631475310862773, "order": 25}, {"M": "M1", "seg1": "Mujer", "seg2": "Secundaria o FP grado sup", "cat": "2", "prop": 0.040074887604086736, "lower": 0.028382417727705913, "upper": 0.05701876392243249, "order": 26}, {"M": "M1", "seg1": "Mujer", "seg2": "Secundaria o FP grado sup", "cat": "3", "prop": 0.06038995948021778, "lower": 0.04511461802959142, "upper": 0.07915715016561083, "order": 27}, {"M": "M1", "seg1": "Mujer", "seg2": "Secundaria o FP grado sup", "cat": "4", "prop": 0.01994447079448384, "lower": 0.011554726228719262, "upper": 0.03529191143335183, "order": 28}, {"M": "M1", "seg1": "Mujer", "seg2": "Secundaria o FP grado sup", "cat": "5", "prop": 0.04057568316864026, "lower": 0.0274908146960367, "upper": 0.05593101762359817, "order": 29}, {"M": "M1", "seg1": "Mujer", "seg2": "Estudios universitarios o m\u00e1s", "cat": "1", "prop": 0.857936445007777, "lower": 0.8223982914615665, "upper": 0.8864514848856646, "order": 30}, {"M": "M1", "seg1": "Mujer", "seg2": "Estudios universitarios o m\u00e1s", "cat": "2", "prop": 0.0463983033416425, "lower": 0.029331808641943055, "upper": 0.07081164812491374, "order": 31}, {"M": "M1", "seg1": "Mujer", "seg2": "Estudios universitarios o m\u00e1s", "cat": "3", "prop": 0.06465847938622023, "lower": 0.047562008550796855, "upper": 0.09216532905842123, "order": 32}, {"M": "M1", "seg1": "Mujer", "seg2": "Estudios universitarios o m\u00e1s", "cat": "4", "prop": 0.017957130454171043, "lower": 0.008181887116504654, "upper": 0.03328958114963797, "order": 33}, {"M": "M1", "seg1": "Mujer", "seg2": "Estudios universitarios o m\u00e1s", "cat": "5", "prop": 0.013049641810189319, "lower": 0.005756574829007273, "upper": 0.027160545891765125, "order": 34}, {"M": "M1", "seg1": "Mujer", "seg2": "Total", "cat": "1", "prop": 0.8327444119624992, "lower": 0.8132300268398513, "upper": 0.8497872621364647, "order": 35}, {"M": "M1", "seg1": "Mujer", "seg2": "Total", "cat": "2", "prop": 0.04540151293482805, "lower": 0.035774103220483314, "upper": 0.05783224818956135, "order": 36}, {"M": "M1", "seg1": "Mujer", "seg2": "Total", "cat": "3", "prop": 0.06125193210432196, "lower": 0.049995392994867716, "upper": 0.07334874460109073, "order": 37}, {"M": "M1", "seg1": "Mujer", "seg2": "Total", "cat": "4", "prop": 0.022980860584689886, "lower": 0.01605821340162664, "upper": 0.031818488945377574, "order": 38}, {"M": "M1", "seg1": "Mujer", "seg2": "Total", "cat": "5", "prop": 0.03762128241366103, "lower": 0.028816186706707655, "upper": 0.04748360897048363, "order": 39}, {"M": "M1", "seg1": "Total", "seg2": "Hasta primaria", "cat": "1", "prop": 0.8261000937693572, "lower": 0.7972182502349756, "upper": 0.8552951573790276, "order": 40}, {"M": "M1", "seg1": "Total", "seg2": "Hasta primaria", "cat": "2", "prop": 0.046498895469320366, "lower": 0.03142086842053376, "upper": 0.06717603322948332, "order": 41}, {"M": "M1", "seg1": "Total", "seg2": "Hasta primaria", "cat": "3", "prop": 0.057948704317976434, "lower": 0.04147018506191182, "upper": 0.07862577721784048, "order": 42}, {"M": "M1", "seg1": "Total", "seg2": "Hasta primaria", "cat": "4", "prop": 0.026017476284044487, "lower": 0.01542611509432698, "upper": 0.04135711883455512, "order": 43}, {"M": "M1", "seg1": "Total", "seg2": "Hasta primaria", "cat": "5", "prop": 0.04343483015930145, "lower": 0.02893192363471283, "upper": 0.06089557271024525, "order": 44}, {"M": "M1", "seg1": "Total", "seg2": "Secundaria o FP grado sup", "cat": "1", "prop": 0.8661748081789838, "lower": 0.8467086575153568, "upper": 0.882230258565735, "order": 45}, {"M": "M1", "seg1": "Total", "seg2": "Secundaria o FP grado sup", "cat": "2", "prop": 0.03784793466873068, "lower": 0.028570879507737446, "upper": 0.04800520246409248, "order": 46}, {"M": "M1", "seg1": "Total", "seg2": "Secundaria o FP grado sup", "cat": "3", "prop": 0.04838064409267981, "lower": 0.038725496913794955, "upper": 0.06170757387880385, "order": 47}, {"M": "M1", "seg1": "Total", "seg2": "Secundaria o FP grado sup", "cat": "4", "prop": 0.01973326288461475, "lower": 0.013356309152460425, "upper": 0.028572351209943628, "order": 48}, {"M": "M1", "seg1": "Total", "seg2": "Secundaria o FP grado sup", "cat": "5", "prop": 0.027863350174990746, "lower": 0.020153686019606334, "upper": 0.037388180336746395, "order": 49}, {"M": "M1", "seg1": "Total", "seg2": "Estudios universitarios o m\u00e1s", "cat": "1", "prop": 0.8605156299346572, "lower": 0.8348554525487009, "upper": 0.884399276487897, "order": 50}, {"M": "M1", "seg1": "Total", "seg2": "Estudios universitarios o m\u00e1s", "cat": "2", "prop": 0.05781929384777227, "lower": 0.04316137548284492, "upper": 0.07580776049973051, "order": 51}, {"M": "M1", "seg1": "Total", "seg2": "Estudios universitarios o m\u00e1s", "cat": "3", "prop": 0.04924546865127834, "lower": 0.03662377049377951, "upper": 0.06499842358092518, "order": 52}, {"M": "M1", "seg1": "Total", "seg2": "Estudios universitarios o m\u00e1s", "cat": "4", "prop": 0.015624239717278094, "lower": 0.008284271316277366, "upper": 0.024613412007088047, "order": 53}, {"M": "M1", "seg1": "Total", "seg2": "Estudios universitarios o m\u00e1s", "cat": "5", "prop": 0.016795367849014087, "lower": 0.007922327007232478, "upper": 0.04852064729929414, "order": 54}, {"M": "M1", "seg1": "Total", "seg2": "Total", "cat": "1", "prop": 0.8562063754126951, "lower": 0.8399280770115595, "upper": 0.8687084608121466, "order": 55}, {"M": "M1", "seg1": "Total", "seg2": "Total", "cat": "2", "prop": 0.04537021888344354, "lower": 0.03856999649703357, "upper": 0.053823042068867795, "order": 56}, {"M": "M1", "seg1": "Total", "seg2": "Total", "cat": "3", "prop": 0.05062136385299186, "lower": 0.04380347464050401, "upper": 0.05864576272584823, "order": 57}, {"M": "M1", "seg1": "Total", "seg2": "Total", "cat": "4", "prop": 0.019865326625987854, "lower": 0.01548082002908975, "upper": 0.02584977007051948, "order": 58}, {"M": "M1", "seg1": "Total", "seg2": "Total", "cat": "5", "prop": 0.02793671522488164, "lower": 0.021837096017949083, "upper": 0.03701519064521862, "order": 59}, {"M": "M2", "seg1": "Hombre", "seg2": "Hasta primaria", "cat": "1", "prop": 0.7936239712458405, "lower": 0.6856717393578312, "upper": 0.8580739227282671, "order": 60}, {"M": "M2", "seg1": "Hombre", "seg2": "Hasta primaria", "cat": "2", "prop": 0.04170880130861524, "lower": 0.017687509263323117, "upper": 0.07999063423124482, "order": 61}, {"M": "M2", "seg1": "Hombre", "seg2": "Hasta primaria", "cat": "3", "prop": 0.09866803750659994, "lower": 0.046540478115374706, "upper": 0.2496427134614307, "order": 62}, {"M": "M2", "seg1": "Hombre", "seg2": "Hasta primaria", "cat": "4", "prop": 0.011796597553405811, "lower": 0.0, "upper": 0.030335314822565018, "order": 63}, {"M": "M2", "seg1": "Hombre", "seg2": "Hasta primaria", "cat": "5", "prop": 0.05420259238553837, "lower": 0.029737064504547685, "upper": 0.09245476364137364, "order": 64}, {"M": "M2", "seg1": "Hombre", "seg2": "Secundaria o FP grado sup", "cat": "1", "prop": 0.8678934198673198, "lower": 0.8326448896693811, "upper": 0.8961456979221762, "order": 65}, {"M": "M2", "seg1": "Hombre", "seg2": "Secundaria o FP grado sup", "cat": "2", "prop": 0.06459591236038084, "lower": 0.043710477301917995, "upper": 0.09282658773275441, "order": 66}, {"M": "M2", "seg1": "Hombre", "seg2": "Secundaria o FP grado sup", "cat": "3", "prop": 0.02532199181995588, "lower": 0.014808087525165535, "upper": 0.042926172016075965, "order": 67}, {"M": "M2", "seg1": "Hombre", "seg2": "Secundaria o FP grado sup", "cat": "4", "prop": 0.015648393036924686, "lower": 0.00687711085022449, "upper": 0.030562732367241153, "order": 68}, {"M": "M2", "seg1": "Hombre", "seg2": "Secundaria o FP grado sup", "cat": "5", "prop": 0.026540282915418684, "lower": 0.014127040917417356, "upper": 0.04414809885450352, "order": 69}, {"M": "M2", "seg1": "Hombre", "seg2": "Estudios universitarios o m\u00e1s", "cat": "1", "prop": 0.8106487037160055, "lower": 0.7515689407177772, "upper": 0.851746342976922, "order": 70}, {"M": "M2", "seg1": "Hombre", "seg2": "Estudios universitarios o m\u00e1s", "cat": "2", "prop": 0.07877910532059058, "lower": 0.053291815151118985, "upper": 0.12402714530221173, "order": 71}, {"M": "M2", "seg1": "Hombre", "seg2": "Estudios universitarios o m\u00e1s", "cat": "3", "prop": 0.06043688522310297, "lower": 0.038923529788408656, "upper": 0.08857218955055632, "order": 72}, {"M": "M2", "seg1": "Hombre", "seg2": "Estudios universitarios o m\u00e1s", "cat": "4", "prop": 0.02189322944846156, "lower": 0.00980922612870269, "upper": 0.042868278960270886, "order": 73}, {"M": "M2", "seg1": "Hombre", "seg2": "Estudios universitarios o m\u00e1s", "cat": "5", "prop": 0.02824207629183944, "lower": 0.011228020213537783, "upper": 0.08369069074696334, "order": 74}, {"M": "M2", "seg1": "Hombre", "seg2": "Total", "cat": "1", "prop": 0.8351700637313021, "lower": 0.8046452471238604, "upper": 0.8602182400844235, "order": 75}, {"M": "M2", "seg1": "Hombre", "seg2": "Total", "cat": "2", "prop": 0.06464652077661552, "lower": 0.04977483117520182, "upper": 0.08276276202836595, "order": 76}, {"M": "M2", "seg1": "Hombre", "seg2": "Total", "cat": "3", "prop": 0.05081762058522763, "lower": 0.03762684810887159, "upper": 0.0800096208101134, "order": 77}, {"M": "M2", "seg1": "Hombre", "seg2": "Total", "cat": "4", "prop": 0.01688549980350415, "lower": 0.010369298275146085, "upper": 0.02577682994899354, "order": 78}, {"M": "M2", "seg1": "Hombre", "seg2": "Total", "cat": "5", "prop": 0.03248029510335082, "lower": 0.021561970127033394, "upper": 0.04669792556493156, "order": 79}, {"M": "M2", "seg1": "Mujer", "seg2": "Hasta primaria", "cat": "1", "prop": 0.7728156765142847, "lower": 0.7181603319611973, "upper": 0.8257538555602637, "order": 80}, {"M": "M2", "seg1": "Mujer", "seg2": "Hasta primaria", "cat": "2", "prop": 0.031763329426359926, "lower": 0.01305927287799261, "upper": 0.06177423260749597, "order": 81}, {"M": "M2", "seg1": "Mujer", "seg2": "Hasta primaria", "cat": "3", "prop": 0.08917739993339972, "lower": 0.05593979831574176, "upper": 0.13125261727327636, "order": 82}, {"M": "M2", "seg1": "Mujer", "seg2": "Hasta primaria", "cat": "4", "prop": 0.02546973614205508, "lower": 0.010208520383592802, "upper": 0.05014188070176541, "order": 83}, {"M": "M2", "seg1": "Mujer", "seg2": "Hasta primaria", "cat": "5", "prop": 0.08077385798390065, "lower": 0.05007997962412911, "upper": 0.1219366611339618, "order": 84}, {"M": "M2", "seg1": "Mujer", "seg2": "Secundaria o FP grado sup", "cat": "1", "prop": 0.8124411504226833, "lower": 0.7731206739959963, "upper": 0.8458181785469262, "order": 85}, {"M": "M2", "seg1": "Mujer", "seg2": "Secundaria o FP grado sup", "cat": "2", "prop": 0.03810451512509242, "lower": 0.024926228979389425, "upper": 0.058225215199232475, "order": 86}, {"M": "M2", "seg1": "Mujer", "seg2": "Secundaria o FP grado sup", "cat": "3", "prop": 0.07601356002561341, "lower": 0.05223665230771121, "upper": 0.11063639580819506, "order": 87}, {"M": "M2", "seg1": "Mujer", "seg2": "Secundaria o FP grado sup", "cat": "4", "prop": 0.01621956157893507, "lower": 0.00855399669211765, "upper": 0.029685539977468766, "order": 88}, {"M": "M2", "seg1": "Mujer", "seg2": "Secundaria o FP grado sup", "cat": "5", "prop": 0.057221212847675784, "lower": 0.03903613709849858, "upper": 0.08478427624774461, "order": 89}, {"M": "M2", "seg1": "Mujer", "seg2": "Estudios universitarios o m\u00e1s", "cat": "1", "prop": 0.8880013795803293, "lower": 0.8553602820202043, "upper": 0.9176730872205127, "order": 90}, {"M": "M2", "seg1": "Mujer", "seg2": "Estudios universitarios o m\u00e1s", "cat": "2", "prop": 0.03714334513669497, "lower": 0.02184854374198219, "upper": 0.05867242002825814, "order": 91}, {"M": "M2", "seg1": "Mujer", "seg2": "Estudios universitarios o m\u00e1s", "cat": "3", "prop": 0.04676400309453259, "lower": 0.029900367021096785, "upper": 0.07147774225288951, "order": 92}, {"M": "M2", "seg1": "Mujer", "seg2": "Estudios universitarios o m\u00e1s", "cat": "4", "prop": 0.015471595065879869, "lower": 0.006557757701154634, "upper": 0.03280697837204282, "order": 93}, {"M": "M2", "seg1": "Mujer", "seg2": "Estudios universitarios o m\u00e1s", "cat": "5", "prop": 0.012619677122563296, "lower": 0.004050640663099849, "upper": 0.030356151677009367, "order": 94}, {"M": "M2", "seg1": "Mujer", "seg2": "Total", "cat": "1", "prop": 0.8260826839342433, "lower": 0.8024875073788943, "upper": 0.8487980694651589, "order": 95}, {"M": "M2", "seg1": "Mujer", "seg2": "Total", "cat": "2", "prop": 0.036345485227922976, "lower": 0.026876923513802213, "upper": 0.047448288045223844, "order": 96}, {"M": "M2", "seg1": "Mujer", "seg2": "Total", "cat": "3", "prop": 0.07022904698406857, "lower": 0.05658246861727706, "upper": 0.09014335808924129, "order": 97}, {"M": "M2", "seg1": "Mujer", "seg2": "Total", "cat": "4", "prop": 0.01813620507215155, "lower": 0.011882961578841073, "upper": 0.026854766953206783, "order": 98}, {"M": "M2", "seg1": "Mujer", "seg2": "Total", "cat": "5", "prop": 0.04920657878161365, "lower": 0.03796468691032357, "upper": 0.06530986250217512, "order": 99}, {"M": "M2", "seg1": "Total", "seg2": "Hasta primaria", "cat": "1", "prop": 0.782044038393023, "lower": 0.7190091523330809, "upper": 0.8244858438256674, "order": 100}, {"M": "M2", "seg1": "Total", "seg2": "Hasta primaria", "cat": "2", "prop": 0.03617409036416446, "lower": 0.020978706102226685, "upper": 0.056683993697385096, "order": 101}, {"M": "M2", "seg1": "Total", "seg2": "Hasta primaria", "cat": "3", "prop": 0.0933864444089484, "lower": 0.06209523909056347, "upper": 0.15140145179846326, "order": 102}, {"M": "M2", "seg1": "Total", "seg2": "Hasta primaria", "cat": "4", "prop": 0.019405775950120396, "lower": 0.010012853686923768, "upper": 0.03537583440134392, "order": 103}, {"M": "M2", "seg1": "Total", "seg2": "Hasta primaria", "cat": "5", "prop": 0.06898965088374356, "lower": 0.04750688608034269, "upper": 0.09644982560358514, "order": 104}, {"M": "M2", "seg1": "Total", "seg2": "Secundaria o FP grado sup", "cat": "1", "prop": 0.8399790669928733, "lower": 0.8167597560465084, "upper": 0.8637510263508111, "order": 105}, {"M": "M2", "seg1": "Total", "seg2": "Secundaria o FP grado sup", "cat": "2", "prop": 0.05126029565850201, "lower": 0.0385101388087007, "upper": 0.06609242297314015, "order": 106}, {"M": "M2", "seg1": "Total", "seg2": "Secundaria o FP grado sup", "cat": "3", "prop": 0.05083983512598251, "lower": 0.037659698627466244, "upper": 0.07025900315841949, "order": 107}, {"M": "M2", "seg1": "Total", "seg2": "Secundaria o FP grado sup", "cat": "4", "prop": 0.015935915989405094, "lower": 0.009978735123301215, "upper": 0.02547526388122629, "order": 108}, {"M": "M2", "seg1": "Total", "seg2": "Secundaria o FP grado sup", "cat": "5", "prop": 0.04198488623323714, "lower": 0.030833393219540598, "upper": 0.056664157662942236, "order": 109}, {"M": "M2", "seg1": "Total", "seg2": "Estudios universitarios o m\u00e1s", "cat": "1", "prop": 0.8493743966950404, "lower": 0.8156920005288174, "upper": 0.8738298139526313, "order": 110}, {"M": "M2", "seg1": "Total", "seg2": "Estudios universitarios o m\u00e1s", "cat": "2", "prop": 0.05793465943925656, "lower": 0.04101661654160917, "upper": 0.08133753626159779, "order": 111}, {"M": "M2", "seg1": "Total", "seg2": "Estudios universitarios o m\u00e1s", "cat": "3", "prop": 0.05359172014596618, "lower": 0.03961451467055539, "upper": 0.07142350057929914, "order": 112}, {"M": "M2", "seg1": "Total", "seg2": "Estudios universitarios o m\u00e1s", "cat": "4", "prop": 0.018678314919070738, "lower": 0.010419254247112889, "upper": 0.03140036176022601, "order": 113}, {"M": "M2", "seg1": "Total", "seg2": "Estudios universitarios o m\u00e1s", "cat": "5", "prop": 0.020420908800666087, "lower": 0.010550701780229776, "upper": 0.04939127640768254, "order": 114}, {"M": "M2", "seg1": "Total", "seg2": "Total", "cat": "1", "prop": 0.8305000620395531, "lower": 0.8116392182772835, "upper": 0.8469918904492264, "order": 115}, {"M": "M2", "seg1": "Total", "seg2": "Total", "cat": "2", "prop": 0.05010262728452046, "lower": 0.040858399759313255, "upper": 0.06077389666332758, "order": 116}, {"M": "M2", "seg1": "Total", "seg2": "Total", "cat": "3", "prop": 0.06079314666054212, "lower": 0.05004751269051446, "upper": 0.07505356576606124, "order": 117}, {"M": "M2", "seg1": "Total", "seg2": "Total", "cat": "4", "prop": 0.017528236857627607, "lower": 0.013098629391218926, "upper": 0.023357016849454456, "order": 118}, {"M": "M2", "seg1": "Total", "seg2": "Total", "cat": "5", "prop": 0.04107592715775672, "lower": 0.0320284932246335, "upper": 0.05173488697047412, "order": 119}, {"M": "M3", "seg1": "Hombre", "seg2": "Hasta primaria", "cat": "1", "prop": 0.7802566464093171, "lower": 0.7237544513057945, "upper": 0.8286343833016584, "order": 120}, {"M": "M3", "seg1": "Hombre", "seg2": "Hasta primaria", "cat": "2", "prop": 0.04915464265132269, "lower": 0.028365786903301073, "upper": 0.08003275075016825, "order": 121}, {"M": "M3", "seg1": "Hombre", "seg2": "Hasta primaria", "cat": "3", "prop": 0.08468293804339554, "lower": 0.054098383352203995, "upper": 0.13567036543497335, "order": 122}, {"M": "M3", "seg1": "Hombre", "seg2": "Hasta primaria", "cat": "4", "prop": 0.020982260191784653, "lower": 0.009162054065825641, "upper": 0.04302374013015568, "order": 123}, {"M": "M3", "seg1": "Hombre", "seg2": "Hasta primaria", "cat": "5", "prop": 0.06492351270418016, "lower": 0.041368135585298386, "upper": 0.09716190871680352, "order": 124}, {"M": "M3", "seg1": "Hombre", "seg2": "Secundaria o FP grado sup", "cat": "1", "prop": 0.8564699673948983, "lower": 0.8251464623237343, "upper": 0.882351339465248, "order": 125}, {"M": "M3", "seg1": "Hombre", "seg2": "Secundaria o FP grado sup", "cat": "2", "prop": 0.04275985266540982, "lower": 0.02947816927807757, "upper": 0.05920641096806617, "order": 126}, {"M": "M3", "seg1": "Hombre", "seg2": "Secundaria o FP grado sup", "cat": "3", "prop": 0.04436350597215745, "lower": 0.029644101697372277, "upper": 0.06622349289886373, "order": 127}, {"M": "M3", "seg1": "Hombre", "seg2": "Secundaria o FP grado sup", "cat": "4", "prop": 0.02700983083482773, "lower": 0.016216550426586297, "upper": 0.04314688064380461, "order": 128}, {"M": "M3", "seg1": "Hombre", "seg2": "Secundaria o FP grado sup", "cat": "5", "prop": 0.029396843132706584, "lower": 0.018263126923514346, "upper": 0.044167955079377125, "order": 129}, {"M": "M3", "seg1": "Hombre", "seg2": "Estudios universitarios o m\u00e1s", "cat": "1", "prop": 0.8088581514740159, "lower": 0.7665243506220982, "upper": 0.8464968741059944, "order": 130}, {"M": "M3", "seg1": "Hombre", "seg2": "Estudios universitarios o m\u00e1s", "cat": "2", "prop": 0.08034071857030203, "lower": 0.05848631343265612, "upper": 0.11072711457125413, "order": 131}, {"M": "M3", "seg1": "Hombre", "seg2": "Estudios universitarios o m\u00e1s", "cat": "3", "prop": 0.07018119631597623, "lower": 0.047919429753588184, "upper": 0.09685810598608889, "order": 132}, {"M": "M3", "seg1": "Hombre", "seg2": "Estudios universitarios o m\u00e1s", "cat": "4", "prop": 0.032357285114883526, "lower": 0.019467093655774786, "upper": 0.05182916966624789, "order": 133}, {"M": "M3", "seg1": "Hombre", "seg2": "Estudios universitarios o m\u00e1s", "cat": "5", "prop": 0.0082626485248224, "lower": 0.002097891195210139, "upper": 0.022916441540568447, "order": 134}, {"M": "M3", "seg1": "Hombre", "seg2": "Total", "cat": "1", "prop": 0.8247813812243863, "lower": 0.8027241579693798, "upper": 0.8450652179953397, "order": 135}, {"M": "M3", "seg1": "Hombre", "seg2": "Total", "cat": "2", "prop": 0.05563183125421839, "lower": 0.04347645040171987, "upper": 0.06792946111949423, "order": 136}, {"M": "M3", "seg1": "Hombre", "seg2": "Total", "cat": "3", "prop": 0.06131924391819991, "lower": 0.049022370909997254, "upper": 0.07892476209107517, "order": 137}, {"M": "M3", "seg1": "Hombre", "seg2": "Total", "cat": "4", "prop": 0.027274795006035506, "lower": 0.01997657293672995, "upper": 0.036338203714695816, "order": 138}, {"M": "M3", "seg1": "Hombre", "seg2": "Total", "cat": "5", "prop": 0.030992748597159937, "lower": 0.02277919653632916, "upper": 0.04157626427688339, "order": 139}, {"M": "M3", "seg1": "Mujer", "seg2": "Hasta primaria", "cat": "1", "prop": 0.7807801762889546, "lower": 0.7349894168655479, "upper": 0.8235836901170495, "order": 140}, {"M": "M3", "seg1": "Mujer", "seg2": "Hasta primaria", "cat": "2", "prop": 0.04514033928693896, "lower": 0.027949179512966795, "upper": 0.06882706626885873, "order": 141}, {"M": "M3", "seg1": "Mujer", "seg2": "Hasta primaria", "cat": "3", "prop": 0.0649927313446606, "lower": 0.042312790954809686, "upper": 0.0961010379856757, "order": 142}, {"M": "M3", "seg1": "Mujer", "seg2": "Hasta primaria", "cat": "4", "prop": 0.052862564752714794, "lower": 0.034279859487316024, "upper": 0.07974074715005144, "order": 143}, {"M": "M3", "seg1": "Mujer", "seg2": "Hasta primaria", "cat": "5", "prop": 0.05622418832673105, "lower": 0.03574976180926323, "upper": 0.08338695879986235, "order": 144}, {"M": "M3", "seg1": "Mujer", "seg2": "Secundaria o FP grado sup", "cat": "1", "prop": 0.8210313686899735, "lower": 0.7882673814815522, "upper": 0.8494299145447133, "order": 145}, {"M": "M3", "seg1": "Mujer", "seg2": "Secundaria o FP grado sup", "cat": "2", "prop": 0.04598041732367108, "lower": 0.031743817828174294, "upper": 0.06363450820541727, "order": 146}, {"M": "M3", "seg1": "Mujer", "seg2": "Secundaria o FP grado sup", "cat": "3", "prop": 0.05541461343140257, "lower": 0.04044468418855723, "upper": 0.07669523008985185, "order": 147}, {"M": "M3", "seg1": "Mujer", "seg2": "Secundaria o FP grado sup", "cat": "4", "prop": 0.02870350329944106, "lower": 0.01757021106708485, "upper": 0.04522569385767935, "order": 148}, {"M": "M3", "seg1": "Mujer", "seg2": "Secundaria o FP grado sup", "cat": "5", "prop": 0.04887009725551172, "lower": 0.035329506115291454, "upper": 0.06873258557834526, "order": 149}, {"M": "M3", "seg1": "Mujer", "seg2": "Estudios universitarios o m\u00e1s", "cat": "1", "prop": 0.8644990492007095, "lower": 0.8320207167601998, "upper": 0.8928357613749194, "order": 150}, {"M": "M3", "seg1": "Mujer", "seg2": "Estudios universitarios o m\u00e1s", "cat": "2", "prop": 0.055905709726399876, "lower": 0.0393695908261636, "upper": 0.08130540319495189, "order": 151}, {"M": "M3", "seg1": "Mujer", "seg2": "Estudios universitarios o m\u00e1s", "cat": "3", "prop": 0.036256599903387886, "lower": 0.021952687890026256, "upper": 0.05711062789202019, "order": 152}, {"M": "M3", "seg1": "Mujer", "seg2": "Estudios universitarios o m\u00e1s", "cat": "4", "prop": 0.031237225331502333, "lower": 0.018724419075951397, "upper": 0.04852633795794284, "order": 153}, {"M": "M3", "seg1": "Mujer", "seg2": "Estudios universitarios o m\u00e1s", "cat": "5", "prop": 0.012101415838000342, "lower": 0.004334823364905344, "upper": 0.02656075565344407, "order": 154}, {"M": "M3", "seg1": "Mujer", "seg2": "Total", "cat": "1", "prop": 0.8233278043246642, "lower": 0.8028853333336519, "upper": 0.8422801810169012, "order": 155}, {"M": "M3", "seg1": "Mujer", "seg2": "Total", "cat": "2", "prop": 0.04873935305476561, "lower": 0.03875563070424405, "upper": 0.06029811903913805, "order": 156}, {"M": "M3", "seg1": "Mujer", "seg2": "Total", "cat": "3", "prop": 0.05221834937337961, "lower": 0.04134030488142633, "upper": 0.06475524978405482, "order": 157}, {"M": "M3", "seg1": "Mujer", "seg2": "Total", "cat": "4", "prop": 0.03592988617480861, "lower": 0.02797153512258137, "upper": 0.04681456234141317, "order": 158}, {"M": "M3", "seg1": "Mujer", "seg2": "Total", "cat": "5", "prop": 0.039784607072382, "lower": 0.03022494619583736, "upper": 0.05052242080314078, "order": 159}, {"M": "M3", "seg1": "Total", "seg2": "Hasta primaria", "cat": "1", "prop": 0.7805470803679575, "lower": 0.7473412770790936, "upper": 0.8131909907470358, "order": 160}, {"M": "M3", "seg1": "Total", "seg2": "Hasta primaria", "cat": "2", "prop": 0.04692766370962667, "lower": 0.033118906675055834, "upper": 0.06496078883364631, "order": 161}, {"M": "M3", "seg1": "Total", "seg2": "Hasta primaria", "cat": "3", "prop": 0.07375957931949491, "lower": 0.05441352954214429, "upper": 0.1023034992282587, "order": 162}, {"M": "M3", "seg1": "Total", "seg2": "Hasta primaria", "cat": "4", "prop": 0.03866820977445811, "lower": 0.025471565091199435, "upper": 0.057147102079448696, "order": 163}, {"M": "M3", "seg1": "Total", "seg2": "Hasta primaria", "cat": "5", "prop": 0.06009746682846289, "lower": 0.04310052311171626, "upper": 0.0782878724456808, "order": 164}, {"M": "M3", "seg1": "Total", "seg2": "Secundaria o FP grado sup", "cat": "1", "prop": 0.8390587836377155, "lower": 0.8178976546238911, "upper": 0.8585297980442117, "order": 165}, {"M": "M3", "seg1": "Total", "seg2": "Secundaria o FP grado sup", "cat": "2", "prop": 0.04434213427687443, "lower": 0.03421496011252343, "upper": 0.0574586762745013, "order": 166}, {"M": "M3", "seg1": "Total", "seg2": "Secundaria o FP grado sup", "cat": "3", "prop": 0.04979297750107977, "lower": 0.03869299662145541, "upper": 0.06239279573618784, "order": 167}, {"M": "M3", "seg1": "Total", "seg2": "Secundaria o FP grado sup", "cat": "4", "prop": 0.027841941685242528, "lower": 0.02035236892406287, "upper": 0.03854134350743235, "order": 168}, {"M": "M3", "seg1": "Total", "seg2": "Secundaria o FP grado sup", "cat": "5", "prop": 0.03896416289908789, "lower": 0.0301061656115711, "upper": 0.0494125076116521, "order": 169}, {"M": "M3", "seg1": "Total", "seg2": "Estudios universitarios o m\u00e1s", "cat": "1", "prop": 0.8372172675478523, "lower": 0.809896778276652, "upper": 0.8603934434771492, "order": 170}, {"M": "M3", "seg1": "Total", "seg2": "Estudios universitarios o m\u00e1s", "cat": "2", "prop": 0.06788665545519537, "lower": 0.05231803761349505, "upper": 0.08650410010824146, "order": 171}, {"M": "M3", "seg1": "Total", "seg2": "Estudios universitarios o m\u00e1s", "cat": "3", "prop": 0.052890469409514224, "lower": 0.03827444606982566, "upper": 0.06931906637551594, "order": 172}, {"M": "M3", "seg1": "Total", "seg2": "Estudios universitarios o m\u00e1s", "cat": "4", "prop": 0.031786411769838555, "lower": 0.02211962288778083, "upper": 0.04344032034560427, "order": 173}, {"M": "M3", "seg1": "Total", "seg2": "Estudios universitarios o m\u00e1s", "cat": "5", "prop": 0.010219195817599716, "lower": 0.005097116350588496, "upper": 0.01927755297186658, "order": 174}, {"M": "M3", "seg1": "Total", "seg2": "Total", "cat": "1", "prop": 0.8240363523060326, "lower": 0.8106431500823832, "upper": 0.8383940660984405, "order": 175}, {"M": "M3", "seg1": "Total", "seg2": "Total", "cat": "2", "prop": 0.052099100664802916, "lower": 0.04372847550151262, "upper": 0.061038527647456695, "order": 176}, {"M": "M3", "seg1": "Total", "seg2": "Total", "cat": "3", "prop": 0.056654592450447176, "lower": 0.048844125350611806, "upper": 0.06650536640487602, "order": 177}, {"M": "M3", "seg1": "Total", "seg2": "Total", "cat": "4", "prop": 0.03171095054273813, "lower": 0.026040096395779953, "upper": 0.03878995246173627, "order": 178}, {"M": "M3", "seg1": "Total", "seg2": "Total", "cat": "5", "prop": 0.035499004035979415, "lower": 0.02954534349340684, "upper": 0.04286552885725934, "order": 179}, {"M": "M4", "seg1": "Hombre", "seg2": "Hasta primaria", "cat": "1", "prop": 0.7558394892681382, "lower": 0.7039365036249472, "upper": 0.8136057180669418, "order": 180}, {"M": "M4", "seg1": "Hombre", "seg2": "Hasta primaria", "cat": "2", "prop": 0.06951226186257088, "lower": 0.04212538401766232, "upper": 0.10564000394159463, "order": 181}, {"M": "M4", "seg1": "Hombre", "seg2": "Hasta primaria", "cat": "3", "prop": 0.090376477924657, "lower": 0.05790583909741966, "upper": 0.129607696867066, "order": 182}, {"M": "M4", "seg1": "Hombre", "seg2": "Hasta primaria", "cat": "4", "prop": 0.05046628308216078, "lower": 0.028899031463797704, "upper": 0.08180591273134018, "order": 183}, {"M": "M4", "seg1": "Hombre", "seg2": "Hasta primaria", "cat": "5", "prop": 0.033805487862473435, "lower": 0.017910012876002693, "upper": 0.056166797271324224, "order": 184}, {"M": "M4", "seg1": "Hombre", "seg2": "Secundaria o FP grado sup", "cat": "1", "prop": 0.8380102330199883, "lower": 0.8030151571979799, "upper": 0.8676572160872176, "order": 185}, {"M": "M4", "seg1": "Hombre", "seg2": "Secundaria o FP grado sup", "cat": "2", "prop": 0.07089065704961606, "lower": 0.050204337158900825, "upper": 0.09685522697750015, "order": 186}, {"M": "M4", "seg1": "Hombre", "seg2": "Secundaria o FP grado sup", "cat": "3", "prop": 0.04677869503599265, "lower": 0.033262685359952575, "upper": 0.0670119304373545, "order": 187}, {"M": "M4", "seg1": "Hombre", "seg2": "Secundaria o FP grado sup", "cat": "4", "prop": 0.02387515580293616, "lower": 0.014722669386492217, "upper": 0.038634516670207, "order": 188}, {"M": "M4", "seg1": "Hombre", "seg2": "Secundaria o FP grado sup", "cat": "5", "prop": 0.020445259091466883, "lower": 0.011257020488510319, "upper": 0.03521564139920135, "order": 189}, {"M": "M4", "seg1": "Hombre", "seg2": "Estudios universitarios o m\u00e1s", "cat": "1", "prop": 0.8320069278094121, "lower": 0.7936376555999642, "upper": 0.8690939339979399, "order": 190}, {"M": "M4", "seg1": "Hombre", "seg2": "Estudios universitarios o m\u00e1s", "cat": "2", "prop": 0.06520116218082253, "lower": 0.04304489380437103, "upper": 0.09513153954764375, "order": 191}, {"M": "M4", "seg1": "Hombre", "seg2": "Estudios universitarios o m\u00e1s", "cat": "3", "prop": 0.0514102266621429, "lower": 0.03450734984503165, "upper": 0.0773953803711014, "order": 192}, {"M": "M4", "seg1": "Hombre", "seg2": "Estudios universitarios o m\u00e1s", "cat": "4", "prop": 0.03113464133729444, "lower": 0.01688712012478859, "upper": 0.0523287558866927, "order": 193}, {"M": "M4", "seg1": "Hombre", "seg2": "Estudios universitarios o m\u00e1s", "cat": "5", "prop": 0.020247042010328033, "lower": 0.009857545840881195, "upper": 0.036874330776555476, "order": 194}, {"M": "M4", "seg1": "Hombre", "seg2": "Total", "cat": "1", "prop": 0.8185239779039899, "lower": 0.7960021820267857, "upper": 0.8401815971653359, "order": 195}, {"M": "M4", "seg1": "Hombre", "seg2": "Total", "cat": "2", "prop": 0.06882407922497505, "lower": 0.055983289562989993, "upper": 0.08521826013982985, "order": 196}, {"M": "M4", "seg1": "Hombre", "seg2": "Total", "cat": "3", "prop": 0.05756784209214845, "lower": 0.04683385951500125, "upper": 0.07198144603210742, "order": 197}, {"M": "M4", "seg1": "Hombre", "seg2": "Total", "cat": "4", "prop": 0.03183609162236382, "lower": 0.0235614989922889, "upper": 0.04171342682359662, "order": 198}, {"M": "M4", "seg1": "Hombre", "seg2": "Total", "cat": "5", "prop": 0.023248009156522975, "lower": 0.016586502862272662, "upper": 0.03333528692327115, "order": 199}, {"M": "M4", "seg1": "Mujer", "seg2": "Hasta primaria", "cat": "1", "prop": 0.7244381060346318, "lower": 0.6735960798652599, "upper": 0.7739183874748021, "order": 200}, {"M": "M4", "seg1": "Mujer", "seg2": "Hasta primaria", "cat": "2", "prop": 0.06466407810705095, "lower": 0.041031404605284615, "upper": 0.09612168142549302, "order": 201}, {"M": "M4", "seg1": "Mujer", "seg2": "Hasta primaria", "cat": "3", "prop": 0.07417008623101605, "lower": 0.049722356281448096, "upper": 0.10593956748682215, "order": 202}, {"M": "M4", "seg1": "Mujer", "seg2": "Hasta primaria", "cat": "4", "prop": 0.06667025561006608, "lower": 0.043999753353718814, "upper": 0.09572885162221317, "order": 203}, {"M": "M4", "seg1": "Mujer", "seg2": "Hasta primaria", "cat": "5", "prop": 0.07005747401723533, "lower": 0.04419504675055985, "upper": 0.10213224892189558, "order": 204}, {"M": "M4", "seg1": "Mujer", "seg2": "Secundaria o FP grado sup", "cat": "1", "prop": 0.8250405217449608, "lower": 0.7937768367156244, "upper": 0.8559193619228231, "order": 205}, {"M": "M4", "seg1": "Mujer", "seg2": "Secundaria o FP grado sup", "cat": "2", "prop": 0.06483659962243787, "lower": 0.046924036923325266, "upper": 0.08777985354868112, "order": 206}, {"M": "M4", "seg1": "Mujer", "seg2": "Secundaria o FP grado sup", "cat": "3", "prop": 0.054926968477425585, "lower": 0.03918320520052052, "upper": 0.07717880080593915, "order": 207}, {"M": "M4", "seg1": "Mujer", "seg2": "Secundaria o FP grado sup", "cat": "4", "prop": 0.029671758283463127, "lower": 0.018259335717049303, "upper": 0.05702828823970179, "order": 208}, {"M": "M4", "seg1": "Mujer", "seg2": "Secundaria o FP grado sup", "cat": "5", "prop": 0.025524151871712506, "lower": 0.016490930309000857, "upper": 0.03964358896462163, "order": 209}, {"M": "M4", "seg1": "Mujer", "seg2": "Estudios universitarios o m\u00e1s", "cat": "1", "prop": 0.8530463362463626, "lower": 0.8177727673911668, "upper": 0.8831271725200773, "order": 210}, {"M": "M4", "seg1": "Mujer", "seg2": "Estudios universitarios o m\u00e1s", "cat": "2", "prop": 0.054451763305573185, "lower": 0.035639160488089905, "upper": 0.0801598538789138, "order": 211}, {"M": "M4", "seg1": "Mujer", "seg2": "Estudios universitarios o m\u00e1s", "cat": "3", "prop": 0.059648234639417264, "lower": 0.04148305763680957, "upper": 0.08174325288791795, "order": 212}, {"M": "M4", "seg1": "Mujer", "seg2": "Estudios universitarios o m\u00e1s", "cat": "4", "prop": 0.021599605263419575, "lower": 0.010681045920093866, "upper": 0.03582461837239888, "order": 213}, {"M": "M4", "seg1": "Mujer", "seg2": "Estudios universitarios o m\u00e1s", "cat": "5", "prop": 0.011254060545227436, "lower": 0.0041849756000565275, "upper": 0.026911868724175617, "order": 214}, {"M": "M4", "seg1": "Mujer", "seg2": "Total", "cat": "1", "prop": 0.8075274720407196, "lower": 0.7847806033910819, "upper": 0.827907126551792, "order": 215}, {"M": "M4", "seg1": "Mujer", "seg2": "Total", "cat": "2", "prop": 0.06147934133259167, "lower": 0.05007077440982494, "upper": 0.07547194734291637, "order": 216}, {"M": "M4", "seg1": "Mujer", "seg2": "Total", "cat": "3", "prop": 0.061490958038155616, "lower": 0.05017861482731665, "upper": 0.07548599217306662, "order": 217}, {"M": "M4", "seg1": "Mujer", "seg2": "Total", "cat": "4", "prop": 0.0368229224234006, "lower": 0.028057653882089393, "upper": 0.04876610940509412, "order": 218}, {"M": "M4", "seg1": "Mujer", "seg2": "Total", "cat": "5", "prop": 0.03267930616513241, "lower": 0.024910155632076696, "upper": 0.04317240165326357, "order": 219}, {"M": "M4", "seg1": "Total", "seg2": "Hasta primaria", "cat": "1", "prop": 0.7381706809242589, "lower": 0.7004193797101242, "upper": 0.7764908749626418, "order": 220}, {"M": "M4", "seg1": "Total", "seg2": "Hasta primaria", "cat": "2", "prop": 0.06678430465905552, "lower": 0.04958787144535781, "upper": 0.08907660159009206, "order": 221}, {"M": "M4", "seg1": "Total", "seg2": "Hasta primaria", "cat": "3", "prop": 0.08125752839777009, "lower": 0.062024354475048823, "upper": 0.10502427201574879, "order": 222}, {"M": "M4", "seg1": "Total", "seg2": "Hasta primaria", "cat": "4", "prop": 0.05958387140226845, "lower": 0.04353574561706844, "upper": 0.07898014456146718, "order": 223}, {"M": "M4", "seg1": "Total", "seg2": "Hasta primaria", "cat": "5", "prop": 0.0542036146166472, "lower": 0.038452479090155894, "upper": 0.07293913609215777, "order": 224}, {"M": "M4", "seg1": "Total", "seg2": "Secundaria o FP grado sup", "cat": "1", "prop": 0.8317769123386388, "lower": 0.809744085833995, "upper": 0.851332970406994, "order": 225}, {"M": "M4", "seg1": "Total", "seg2": "Secundaria o FP grado sup", "cat": "2", "prop": 0.06798104090113875, "lower": 0.05520360915263746, "upper": 0.08367251005707171, "order": 226}, {"M": "M4", "seg1": "Total", "seg2": "Secundaria o FP grado sup", "cat": "3", "prop": 0.050694803905553296, "lower": 0.039472682872030804, "upper": 0.06381140881889565, "order": 227}, {"M": "M4", "seg1": "Total", "seg2": "Secundaria o FP grado sup", "cat": "4", "prop": 0.026661037566780954, "lower": 0.01846228072211746, "upper": 0.03881588676861072, "order": 228}, {"M": "M4", "seg1": "Total", "seg2": "Secundaria o FP grado sup", "cat": "5", "prop": 0.022886205287888303, "lower": 0.016377450988750746, "upper": 0.032148224162092634, "order": 229}, {"M": "M4", "seg1": "Total", "seg2": "Estudios universitarios o m\u00e1s", "cat": "1", "prop": 0.8429076840563554, "lower": 0.8181728228660403, "upper": 0.8663467341936711, "order": 230}, {"M": "M4", "seg1": "Total", "seg2": "Estudios universitarios o m\u00e1s", "cat": "2", "prop": 0.059631776649313614, "lower": 0.04452782951514602, "upper": 0.07817959790725935, "order": 231}, {"M": "M4", "seg1": "Total", "seg2": "Estudios universitarios o m\u00e1s", "cat": "3", "prop": 0.05567843207246848, "lower": 0.04331796358138857, "upper": 0.0731133596020227, "order": 232}, {"M": "M4", "seg1": "Total", "seg2": "Estudios universitarios o m\u00e1s", "cat": "4", "prop": 0.026194430952644215, "lower": 0.017473738519264124, "upper": 0.037683139397286625, "order": 233}, {"M": "M4", "seg1": "Total", "seg2": "Estudios universitarios o m\u00e1s", "cat": "5", "prop": 0.015587676269218403, "lower": 0.009281979436108544, "upper": 0.027088385411540364, "order": 234}, {"M": "M4", "seg1": "Total", "seg2": "Total", "cat": "1", "prop": 0.8128931079689796, "lower": 0.7974588924692795, "upper": 0.828057242359657, "order": 235}, {"M": "M4", "seg1": "Total", "seg2": "Total", "cat": "2", "prop": 0.06506313331242936, "lower": 0.05530362392174674, "upper": 0.07610131340460681, "order": 236}, {"M": "M4", "seg1": "Total", "seg2": "Total", "cat": "3", "prop": 0.05957671253759746, "lower": 0.05200898169477187, "upper": 0.07049827992509092, "order": 237}, {"M": "M4", "seg1": "Total", "seg2": "Total", "cat": "4", "prop": 0.03438964781354739, "lower": 0.027812592193130235, "upper": 0.041105802588074426, "order": 238}, {"M": "M4", "seg1": "Total", "seg2": "Total", "cat": "5", "prop": 0.028077398367446035, "lower": 0.02249176570638726, "upper": 0.0342845049826255, "order": 239}, {"M": "Mz1", "seg1": "Hombre", "seg2": "Hasta primaria", "cat": "1", "prop": 0.6847951124182767, "lower": 0.6239947270609912, "upper": 0.7386344642090631, "order": 240}, {"M": "Mz1", "seg1": "Hombre", "seg2": "Hasta primaria", "cat": "2", "prop": 0.08190213162932956, "lower": 0.05335031024883576, "upper": 0.12215600220384648, "order": 241}, {"M": "Mz1", "seg1": "Hombre", "seg2": "Hasta primaria", "cat": "3", "prop": 0.10401782936602016, "lower": 0.0707967424084328, "upper": 0.15334412509164727, "order": 242}, {"M": "Mz1", "seg1": "Hombre", "seg2": "Hasta primaria", "cat": "4", "prop": 0.04799256385069754, "lower": 0.027475034665260353, "upper": 0.0773706979625491, "order": 243}, {"M": "Mz1", "seg1": "Hombre", "seg2": "Hasta primaria", "cat": "5", "prop": 0.08129236273567596, "lower": 0.052874246456907345, "upper": 0.11659774968887655, "order": 244}, {"M": "Mz1", "seg1": "Hombre", "seg2": "Secundaria o FP grado sup", "cat": "1", "prop": 0.7994612243592595, "lower": 0.756408264953554, "upper": 0.8339797582459215, "order": 245}, {"M": "Mz1", "seg1": "Hombre", "seg2": "Secundaria o FP grado sup", "cat": "2", "prop": 0.06260706892465842, "lower": 0.04427807415133609, "upper": 0.08864297900287138, "order": 246}, {"M": "Mz1", "seg1": "Hombre", "seg2": "Secundaria o FP grado sup", "cat": "3", "prop": 0.08682303006983477, "lower": 0.06373479382763057, "upper": 0.12027045792245525, "order": 247}, {"M": "Mz1", "seg1": "Hombre", "seg2": "Secundaria o FP grado sup", "cat": "4", "prop": 0.015055935851668794, "lower": 0.005872694586493601, "upper": 0.03174157678903668, "order": 248}, {"M": "Mz1", "seg1": "Hombre", "seg2": "Secundaria o FP grado sup", "cat": "5", "prop": 0.03605274079457842, "lower": 0.021482064964433546, "upper": 0.05784295758341407, "order": 249}, {"M": "Mz1", "seg1": "Hombre", "seg2": "Estudios universitarios o m\u00e1s", "cat": "1", "prop": 0.7750160649204347, "lower": 0.7032494524788393, "upper": 0.8319796053711916, "order": 250}, {"M": "Mz1", "seg1": "Hombre", "seg2": "Estudios universitarios o m\u00e1s", "cat": "2", "prop": 0.0945287961527107, "lower": 0.05925784388332807, "upper": 0.1411462781587568, "order": 251}, {"M": "Mz1", "seg1": "Hombre", "seg2": "Estudios universitarios o m\u00e1s", "cat": "3", "prop": 0.09072709821220509, "lower": 0.05225241622600665, "upper": 0.15259168776193152, "order": 252}, {"M": "Mz1", "seg1": "Hombre", "seg2": "Estudios universitarios o m\u00e1s", "cat": "4", "prop": 0.025922908410817937, "lower": 0.00962187776338669, "upper": 0.06107422486072509, "order": 253}, {"M": "Mz1", "seg1": "Hombre", "seg2": "Estudios universitarios o m\u00e1s", "cat": "5", "prop": 0.013805132303831453, "lower": 0.004142373029283826, "upper": 0.0374551643498135, "order": 254}, {"M": "Mz1", "seg1": "Hombre", "seg2": "Total", "cat": "1", "prop": 0.7614994950068872, "lower": 0.7337548944317439, "upper": 0.789104337554667, "order": 255}, {"M": "Mz1", "seg1": "Hombre", "seg2": "Total", "cat": "2", "prop": 0.07472282349323602, "lower": 0.05867455251561205, "upper": 0.09331936590834021, "order": 256}, {"M": "Mz1", "seg1": "Hombre", "seg2": "Total", "cat": "3", "prop": 0.09256469712369061, "lower": 0.07415051843177041, "upper": 0.1140797519294475, "order": 257}, {"M": "Mz1", "seg1": "Hombre", "seg2": "Total", "cat": "4", "prop": 0.026752096600779495, "lower": 0.017274062042792897, "upper": 0.038130851159747334, "order": 258}, {"M": "Mz1", "seg1": "Hombre", "seg2": "Total", "cat": "5", "prop": 0.044460887775406584, "lower": 0.03256913026787028, "upper": 0.05882118818962861, "order": 259}, {"M": "Mz1", "seg1": "Mujer", "seg2": "Hasta primaria", "cat": "1", "prop": 0.713782575080517, "lower": 0.6445537947097097, "upper": 0.7697078646000209, "order": 260}, {"M": "Mz1", "seg1": "Mujer", "seg2": "Hasta primaria", "cat": "2", "prop": 0.011334710099231036, "lower": 0.004257039362337417, "upper": 0.02508261750901536, "order": 261}, {"M": "Mz1", "seg1": "Mujer", "seg2": "Hasta primaria", "cat": "3", "prop": 0.12252894333586312, "lower": 0.07994167701025527, "upper": 0.186568350121114, "order": 262}, {"M": "Mz1", "seg1": "Mujer", "seg2": "Hasta primaria", "cat": "4", "prop": 0.04928809873328, "lower": 0.027278433863946686, "upper": 0.0806734285237655, "order": 263}, {"M": "Mz1", "seg1": "Mujer", "seg2": "Hasta primaria", "cat": "5", "prop": 0.10306567275110866, "lower": 0.072661825162142, "upper": 0.14501393729292705, "order": 264}, {"M": "Mz1", "seg1": "Mujer", "seg2": "Secundaria o FP grado sup", "cat": "1", "prop": 0.7881306063077869, "lower": 0.7501808790289298, "upper": 0.8209338187111096, "order": 265}, {"M": "Mz1", "seg1": "Mujer", "seg2": "Secundaria o FP grado sup", "cat": "2", "prop": 0.07184620710590939, "lower": 0.05056447070421388, "upper": 0.09839279858059433, "order": 266}, {"M": "Mz1", "seg1": "Mujer", "seg2": "Secundaria o FP grado sup", "cat": "3", "prop": 0.05934551545591434, "lower": 0.039576264223933504, "upper": 0.08100455298208624, "order": 267}, {"M": "Mz1", "seg1": "Mujer", "seg2": "Secundaria o FP grado sup", "cat": "4", "prop": 0.03514081244117308, "lower": 0.020967012478831704, "upper": 0.054312596997078494, "order": 268}, {"M": "Mz1", "seg1": "Mujer", "seg2": "Secundaria o FP grado sup", "cat": "5", "prop": 0.04553685868921625, "lower": 0.03140549453077668, "upper": 0.06985817538705862, "order": 269}, {"M": "Mz1", "seg1": "Mujer", "seg2": "Estudios universitarios o m\u00e1s", "cat": "1", "prop": 0.8094276563288846, "lower": 0.7601065804784306, "upper": 0.8558697466932261, "order": 270}, {"M": "Mz1", "seg1": "Mujer", "seg2": "Estudios universitarios o m\u00e1s", "cat": "2", "prop": 0.07992463917466767, "lower": 0.05287044978915519, "upper": 0.11826811488448759, "order": 271}, {"M": "Mz1", "seg1": "Mujer", "seg2": "Estudios universitarios o m\u00e1s", "cat": "3", "prop": 0.050500478360381504, "lower": 0.031144309360552246, "upper": 0.08428309626174756, "order": 272}, {"M": "Mz1", "seg1": "Mujer", "seg2": "Estudios universitarios o m\u00e1s", "cat": "4", "prop": 0.031699373833417775, "lower": 0.015894379903041798, "upper": 0.05660399084097529, "order": 273}, {"M": "Mz1", "seg1": "Mujer", "seg2": "Estudios universitarios o m\u00e1s", "cat": "5", "prop": 0.02844785230264841, "lower": 0.013150988325447284, "upper": 0.055120120717359236, "order": 274}, {"M": "Mz1", "seg1": "Mujer", "seg2": "Total", "cat": "1", "prop": 0.7668010883307671, "lower": 0.7370423105429763, "upper": 0.7939691075124298, "order": 275}, {"M": "Mz1", "seg1": "Mujer", "seg2": "Total", "cat": "2", "prop": 0.052367674897654516, "lower": 0.04016132127803235, "upper": 0.06690028211380833, "order": 276}, {"M": "Mz1", "seg1": "Mujer", "seg2": "Total", "cat": "3", "prop": 0.07959030994473534, "lower": 0.06059414847031044, "upper": 0.10371065004133252, "order": 277}, {"M": "Mz1", "seg1": "Mujer", "seg2": "Total", "cat": "4", "prop": 0.03933936647432249, "lower": 0.02781633687323923, "upper": 0.05272196830973807, "order": 278}, {"M": "Mz1", "seg1": "Mujer", "seg2": "Total", "cat": "5", "prop": 0.061901560352520466, "lower": 0.04766706737099178, "upper": 0.08042353652577407, "order": 279}, {"M": "Mz1", "seg1": "Total", "seg2": "Hasta primaria", "cat": "1", "prop": 0.7007860435123437, "lower": 0.6582787147781133, "upper": 0.7438498353832325, "order": 280}, {"M": "Mz1", "seg1": "Total", "seg2": "Hasta primaria", "cat": "2", "prop": 0.04297362007513568, "lower": 0.02807905607339327, "upper": 0.06192743429356813, "order": 281}, {"M": "Mz1", "seg1": "Total", "seg2": "Hasta primaria", "cat": "3", "prop": 0.11422948367378984, "lower": 0.08405073736867541, "upper": 0.15290505561947754, "order": 282}, {"M": "Mz1", "seg1": "Total", "seg2": "Hasta primaria", "cat": "4", "prop": 0.048707245548738065, "lower": 0.03202799370149272, "upper": 0.06969118971516049, "order": 283}, {"M": "Mz1", "seg1": "Total", "seg2": "Hasta primaria", "cat": "5", "prop": 0.09330360718999256, "lower": 0.07294037876825196, "upper": 0.12355454985222306, "order": 284}, {"M": "Mz1", "seg1": "Total", "seg2": "Secundaria o FP grado sup", "cat": "1", "prop": 0.794329219820224, "lower": 0.76569006913088, "upper": 0.819105219146879, "order": 285}, {"M": "Mz1", "seg1": "Total", "seg2": "Secundaria o FP grado sup", "cat": "2", "prop": 0.06679177437210701, "lower": 0.05088169753651279, "upper": 0.08489953510810297, "order": 286}, {"M": "Mz1", "seg1": "Total", "seg2": "Secundaria o FP grado sup", "cat": "3", "prop": 0.07437757218929769, "lower": 0.057936699520792806, "upper": 0.09453556256090911, "order": 287}, {"M": "Mz1", "seg1": "Total", "seg2": "Secundaria o FP grado sup", "cat": "4", "prop": 0.024153028115749535, "lower": 0.016034897069738086, "upper": 0.03556617211968316, "order": 288}, {"M": "Mz1", "seg1": "Total", "seg2": "Secundaria o FP grado sup", "cat": "5", "prop": 0.040348405502621774, "lower": 0.028931280178894417, "upper": 0.05362995583355327, "order": 289}, {"M": "Mz1", "seg1": "Total", "seg2": "Estudios universitarios o m\u00e1s", "cat": "1", "prop": 0.793149743561036, "lower": 0.7490261283601294, "upper": 0.8313979753792669, "order": 290}, {"M": "Mz1", "seg1": "Total", "seg2": "Estudios universitarios o m\u00e1s", "cat": "2", "prop": 0.08683292744633934, "lower": 0.0626031035009485, "upper": 0.11627399704152476, "order": 291}, {"M": "Mz1", "seg1": "Total", "seg2": "Estudios universitarios o m\u00e1s", "cat": "3", "prop": 0.06952910743833234, "lower": 0.04756310455948355, "upper": 0.10453424342590859, "order": 292}, {"M": "Mz1", "seg1": "Total", "seg2": "Estudios universitarios o m\u00e1s", "cat": "4", "prop": 0.028966899210564823, "lower": 0.01665521604213015, "upper": 0.048621709857220065, "order": 293}, {"M": "Mz1", "seg1": "Total", "seg2": "Estudios universitarios o m\u00e1s", "cat": "5", "prop": 0.021521322343727462, "lower": 0.01130272766963093, "upper": 0.0384613732142459, "order": 294}, {"M": "Mz1", "seg1": "Total", "seg2": "Total", "cat": "1", "prop": 0.7641535002471367, "lower": 0.7434785095109044, "upper": 0.7839678952557833, "order": 295}, {"M": "Mz1", "seg1": "Total", "seg2": "Total", "cat": "2", "prop": 0.06353171963168826, "lower": 0.05304111225833776, "upper": 0.07573200546799172, "order": 296}, {"M": "Mz1", "seg1": "Total", "seg2": "Total", "cat": "3", "prop": 0.08606965130286703, "lower": 0.07285652231761892, "upper": 0.1026017147001108, "order": 297}, {"M": "Mz1", "seg1": "Total", "seg2": "Total", "cat": "4", "prop": 0.0330533494815585, "lower": 0.02552371933203388, "upper": 0.041736688739416036, "order": 298}, {"M": "Mz1", "seg1": "Total", "seg2": "Total", "cat": "5", "prop": 0.053191779336749484, "lower": 0.043439550054367254, "upper": 0.06455061454468114, "order": 299}]}}