{"config": {"view": {"continuousWidth": 400, "continuousHeight": 300}, "title": {"dx": 30, "dy": -15, "fontSize": 15}}, "vconcat": [{"facet": {"column": {"field": "seg2", "header": {"labelFontSize": 15}, "sort": {"field": "order"}, "title": null, "type": "nominal"}, "row": {"field": "row", "header": {"labels": false, "titleFontSize": 15, "titlePadding": 0}, "sort": {"field": "order"}, "title": "Absoluto (puntos porcentuales)", "type": "nominal"}}, "spec": {"layer": [{"mark": "rule", "encoding": {"y": {"aggregate": "mean", "field": "zero", "type": "quantitative"}}, "transform": [{"calculate": "0", "as": "zero"}]}, {"mark": {"type": "errorbar", "ticks": true}, "encoding": {"color": {"field": "seg1", "legend": {"labelFontSize": 12, "symbolSize": 400}, "sort": {"field": "order"}, "title": null, "type": "nominal"}, "tooltip": {"value": null}, "x": {"axis": {"labelAngle": 0, "labelFontSize": 11}, "field": "M", "sort": {"field": "order"}, "title": null, "type": "nominal"}, "y": {"axis": {"labelFontSize": 11}, "field": "lower", "title": null, "type": "quantitative"}, "y2": {"field": "upper"}}}, {"mark": {"type": "line", "point": {"size": 50}}, "encoding": {"color": {"field": "seg1", "legend": {"labelFontSize": 12, "symbolSize": 400}, "sort": {"field": "order"}, "title": null, "type": "nominal"}, "tooltip": [{"field": "seg1", "title": "Grupo", "type": "nominal"}, {"field": "prop", "format": ".1f", "title": "Estimaci\u00f3n", "type": "quantitative"}, {"field": "lower", "format": ".1f", "title": "L\u00edmite inferior", "type": "quantitative"}, {"field": "upper", "format": ".1f", "title": "L\u00edmite superior", "type": "quantitative"}], "x": {"axis": {"labelAngle": 0, "labelFontSize": 11}, "field": "M", "sort": {"field": "order"}, "title": null, "type": "nominal"}, "y": {"axis": {"labelFontSize": 11}, "field": "prop", "title": null, "type": "quantitative"}}, "selection": {"selector3574": {"type": "interval", "bind": "scales", "encodings": ["x", "y"]}}}], "height": 175, "width": 175}, "resolve": {"axis": {"x": "independent", "y": "independent"}}, "transform": [{"calculate": "datum.seg1 == 'Total'", "as": "row"}, {"filter": "datum.type == 'absolute'"}]}, {"facet": {"column": {"field": "seg2", "header": {"labelFontSize": 15}, "sort": {"field": "order"}, "title": null, "type": "nominal"}, "row": {"field": "row", "header": {"labels": false, "titleFontSize": 15, "titlePadding": 0}, "sort": {"field": "order"}, "title": "Relativo (%)", "type": "nominal"}}, "spec": {"layer": [{"mark": "rule", "encoding": {"y": {"aggregate": "mean", "field": "zero", "type": "quantitative"}}, "transform": [{"calculate": "0", "as": "zero"}]}, {"mark": {"type": "errorbar", "ticks": true}, "encoding": {"color": {"field": "seg1", "legend": {"labelFontSize": 12, "symbolSize": 400}, "sort": {"field": "order"}, "title": null, "type": "nominal"}, "tooltip": {"value": null}, "x": {"axis": {"labelAngle": 0, "labelFontSize": 11}, "field": "M", "sort": {"field": "order"}, "title": null, "type": "nominal"}, "y": {"axis": {"labelFontSize": 11}, "field": "lower", "title": null, "type": "quantitative"}, "y2": {"field": "upper"}}}, {"mark": {"type": "line", "point": {"size": 50}}, "encoding": {"color": {"field": "seg1", "legend": {"labelFontSize": 12, "symbolSize": 400}, "sort": {"field": "order"}, "title": null, "type": "nominal"}, "tooltip": [{"field": "seg1", "title": "Grupo", "type": "nominal"}, {"field": "prop", "format": ".1f", "title": "Estimaci\u00f3n", "type": "quantitative"}, {"field": "lower", "format": ".1f", "title": "L\u00edmite inferior", "type": "quantitative"}, {"field": "upper", "format": ".1f", "title": "L\u00edmite superior", "type": "quantitative"}], "x": {"axis": {"labelAngle": 0, "labelFontSize": 11}, "field": "M", "sort": {"field": "order"}, "title": null, "type": "nominal"}, "y": {"axis": {"labelFontSize": 11}, "field": "prop", "title": null, "type": "quantitative"}}, "selection": {"selector3575": {"type": "interval", "bind": "scales", "encodings": ["x", "y"]}}}], "height": 175, "width": 175}, "resolve": {"axis": {"x": "independent", "y": "independent"}}, "transform": [{"calculate": "datum.seg1 == 'Total'", "as": "row"}, {"filter": "datum.type == 'relative'"}]}], "data": {"name": "data-07e17a0a5651dc276dda8c86fab147aa"}, "title": {"text": ["Poblaci\u00f3n que se ha sentido tranquila en ning\u00fan momento o casi ning\u00fan momento en la \u00faltima semana, cambio en cada medici\u00f3n seg\u00fan sexo y", "grado de urbanizaci\u00f3n (puntos porcentuales / porcentajes e intervalos de confianza al 95%)"], "subtitle": "Fuente: Encuesta Sanitaria y Social de Andaluc\u00eda. C\u00f3digo de variable: P18_6_R"}, "transform": [{"filter": "indexof(datum.M, 'M') != -1"}], "$schema": "https://vega.github.io/schema/vega-lite/v4.17.0.json", "datasets": {"data-07e17a0a5651dc276dda8c86fab147aa": [{"type": "absolute", "M": "M2/M1", "seg1": "Hombre", "seg2": "Urbano", "prop": -2.780876092899106, "lower": -6.378858910578465, "upper": 2.169858989373185, "order": 0}, {"type": "absolute", "M": "M2/M1", "seg1": "Hombre", "seg2": "Intermedio", "prop": -2.825846056520188, "lower": -7.083448641180472, "upper": 0.24621918345783564, "order": 1}, {"type": "absolute", "M": "M2/M1", "seg1": "Hombre", "seg2": "Rural", "prop": -0.37764137980655854, "lower": -6.187649456919674, "upper": 11.032907733629175, "order": 2}, {"type": "absolute", "M": "M2/M1", "seg1": "Hombre", "seg2": "Total", "prop": -2.4964044752649843, "lower": -5.083345558762261, "upper": 0.01002114782747919, "order": 3}, {"type": "absolute", "M": "M2/M1", "seg1": "Mujer", "seg2": "Urbano", "prop": -7.3706319242769425, "lower": -10.864763963177682, "upper": -4.205126188106642, "order": 4}, {"type": "absolute", "M": "M2/M1", "seg1": "Mujer", "seg2": "Intermedio", "prop": -3.8353697475086683, "lower": -7.787282664503454, "upper": 0.5625045349750095, "order": 5}, {"type": "absolute", "M": "M2/M1", "seg1": "Mujer", "seg2": "Rural", "prop": -7.120805790546418, "lower": -13.552960775926334, "upper": -1.2959932558565765, "order": 6}, {"type": "absolute", "M": "M2/M1", "seg1": "Mujer", "seg2": "Total", "prop": -5.970081747004738, "lower": -8.339142079390163, "upper": -3.583440427017105, "order": 7}, {"type": "absolute", "M": "M2/M1", "seg1": "Total", "seg2": "Urbano", "prop": -5.18710045776897, "lower": -7.725480569025196, "upper": -2.3533649735308444, "order": 8}, {"type": "absolute", "M": "M2/M1", "seg1": "Total", "seg2": "Intermedio", "prop": -3.3330609855372866, "lower": -6.270154915680075, "upper": -0.8115746752357418, "order": 9}, {"type": "absolute", "M": "M2/M1", "seg1": "Total", "seg2": "Rural", "prop": -3.7022201858742623, "lower": -7.923768059653927, "upper": 2.301885602682754, "order": 10}, {"type": "absolute", "M": "M2/M1", "seg1": "Total", "seg2": "Total", "prop": -4.278255482172042, "lower": -6.054235773445202, "upper": -2.5697268445799315, "order": 11}, {"type": "absolute", "M": "M3/M1", "seg1": "Hombre", "seg2": "Urbano", "prop": -1.7028852154466867, "lower": -5.170649869721404, "upper": 2.779392587853862, "order": 12}, {"type": "absolute", "M": "M3/M1", "seg1": "Hombre", "seg2": "Intermedio", "prop": -2.2034356447823233, "lower": -6.022023443104503, "upper": 0.9046863680001778, "order": 13}, {"type": "absolute", "M": "M3/M1", "seg1": "Hombre", "seg2": "Rural", "prop": 0.67090307462198, "lower": -5.037082365530232, "upper": 5.956463896166513, "order": 14}, {"type": "absolute", "M": "M3/M1", "seg1": "Hombre", "seg2": "Total", "prop": -1.606462277362128, "lower": -4.01429580733641, "upper": 0.9070869328627107, "order": 15}, {"type": "absolute", "M": "M3/M1", "seg1": "Mujer", "seg2": "Urbano", "prop": -2.5235736904034884, "lower": -5.800877255864578, "upper": 0.757157302016983, "order": 16}, {"type": "absolute", "M": "M3/M1", "seg1": "Mujer", "seg2": "Intermedio", "prop": -1.3302509509940412, "lower": -5.222409702672201, "upper": 2.5263937070200675, "order": 17}, {"type": "absolute", "M": "M3/M1", "seg1": "Mujer", "seg2": "Rural", "prop": -2.515960053764939, "lower": -9.805587614591664, "upper": 4.421814586580269, "order": 18}, {"type": "absolute", "M": "M3/M1", "seg1": "Mujer", "seg2": "Total", "prop": -2.0604624419041846, "lower": -4.396482155823218, "upper": 0.3498290874091983, "order": 19}, {"type": "absolute", "M": "M3/M1", "seg1": "Total", "seg2": "Urbano", "prop": -2.1214764138166227, "lower": -4.6799273051220736, "upper": 0.6727244723183655, "order": 20}, {"type": "absolute", "M": "M3/M1", "seg1": "Total", "seg2": "Intermedio", "prop": -1.8001265473554142, "lower": -4.556040677906525, "upper": 0.6494891166100183, "order": 21}, {"type": "absolute", "M": "M3/M1", "seg1": "Total", "seg2": "Rural", "prop": -0.8947182503218104, "lower": -5.43547607628941, "upper": 3.294240387205526, "order": 22}, {"type": "absolute", "M": "M3/M1", "seg1": "Total", "seg2": "Total", "prop": -1.8426021342007826, "lower": -3.698721356059293, "upper": -0.18499034402030698, "order": 23}, {"type": "absolute", "M": "M4/M1", "seg1": "Hombre", "seg2": "Urbano", "prop": -2.8121121079034457, "lower": -6.434689091932346, "upper": 0.3294140685721986, "order": 24}, {"type": "absolute", "M": "M4/M1", "seg1": "Hombre", "seg2": "Intermedio", "prop": 0.28854784047311066, "lower": -3.928227182796257, "upper": 5.135980939191794, "order": 25}, {"type": "absolute", "M": "M4/M1", "seg1": "Hombre", "seg2": "Rural", "prop": -0.099110110250486, "lower": -5.990704791184965, "upper": 5.198947452934154, "order": 26}, {"type": "absolute", "M": "M4/M1", "seg1": "Hombre", "seg2": "Total", "prop": -1.2365827854979181, "lower": -3.662660352325143, "upper": 1.0526376909742172, "order": 27}, {"type": "absolute", "M": "M4/M1", "seg1": "Mujer", "seg2": "Urbano", "prop": -3.4237252247577787, "lower": -7.06589191145372, "upper": 0.010944571253613072, "order": 28}, {"type": "absolute", "M": "M4/M1", "seg1": "Mujer", "seg2": "Intermedio", "prop": -0.47284428039059134, "lower": -4.32239177336879, "upper": 3.7069474024541824, "order": 29}, {"type": "absolute", "M": "M4/M1", "seg1": "Mujer", "seg2": "Rural", "prop": -3.1475022557838903, "lower": -10.145884772709971, "upper": 3.1328378404497794, "order": 30}, {"type": "absolute", "M": "M4/M1", "seg1": "Mujer", "seg2": "Total", "prop": -2.2609157933915878, "lower": -4.707076826285419, "upper": -0.10231239480205587, "order": 31}, {"type": "absolute", "M": "M4/M1", "seg1": "Total", "seg2": "Urbano", "prop": -3.118739730069828, "lower": -5.582494187549024, "upper": -0.6296144090825311, "order": 32}, {"type": "absolute", "M": "M4/M1", "seg1": "Total", "seg2": "Intermedio", "prop": -0.10813088693618356, "lower": -3.0198304600802484, "upper": 2.979050924977791, "order": 33}, {"type": "absolute", "M": "M4/M1", "seg1": "Total", "seg2": "Rural", "prop": -1.5975902816215248, "lower": -6.507888171119365, "upper": 2.2790869810245624, "order": 34}, {"type": "absolute", "M": "M4/M1", "seg1": "Total", "seg2": "Total", "prop": -1.7579392362964839, "lower": -3.552332432598209, "upper": -0.012119325895485743, "order": 35}, {"type": "absolute", "M": "Mz1/M1", "seg1": "Hombre", "seg2": "Urbano", "prop": 83.58495435645786, "lower": 79.76427043324503, "upper": 86.69455120883929, "order": 36}, {"type": "absolute", "M": "Mz1/M1", "seg1": "Hombre", "seg2": "Intermedio", "prop": 85.85224552424131, "lower": 80.5683630078203, "upper": 89.54915279177415, "order": 37}, {"type": "absolute", "M": "Mz1/M1", "seg1": "Hombre", "seg2": "Rural", "prop": null, "lower": null, "upper": null, "order": 38}, {"type": "absolute", "M": "Mz1/M1", "seg1": "Hombre", "seg2": "Total", "prop": 84.69414351225299, "lower": 81.79139662334248, "upper": 87.10587416676302, "order": 39}, {"type": "absolute", "M": "Mz1/M1", "seg1": "Mujer", "seg2": "Urbano", "prop": 70.10723173941797, "lower": 66.58999867305215, "upper": 73.37588921754052, "order": 40}, {"type": "absolute", "M": "Mz1/M1", "seg1": "Mujer", "seg2": "Intermedio", "prop": 69.82132755002984, "lower": 62.75041172300055, "upper": 74.9553146853127, "order": 41}, {"type": "absolute", "M": "Mz1/M1", "seg1": "Mujer", "seg2": "Rural", "prop": null, "lower": null, "upper": null, "order": 42}, {"type": "absolute", "M": "Mz1/M1", "seg1": "Mujer", "seg2": "Total", "prop": 70.45071638151856, "lower": 67.51451319996741, "upper": 73.06484941850573, "order": 43}, {"type": "absolute", "M": "Mz1/M1", "seg1": "Total", "seg2": "Urbano", "prop": 76.63419103777004, "lower": 74.01438173295554, "upper": 79.13240958071003, "order": 44}, {"type": "absolute", "M": "Mz1/M1", "seg1": "Total", "seg2": "Intermedio", "prop": 78.02180848878628, "lower": 74.27476001717656, "upper": 81.08463284171864, "order": 45}, {"type": "absolute", "M": "Mz1/M1", "seg1": "Total", "seg2": "Rural", "prop": null, "lower": null, "upper": null, "order": 46}, {"type": "absolute", "M": "Mz1/M1", "seg1": "Total", "seg2": "Total", "prop": 77.48377339265443, "lower": 75.62882952065083, "upper": 79.22109633543852, "order": 47}, {"type": "relative", "M": "M2/M1", "seg1": "Hombre", "seg2": "Urbano", "prop": -31.47083119822217, "lower": -59.83293823108523, "upper": 34.591240137805144, "order": 48}, {"type": "relative", "M": "M2/M1", "seg1": "Hombre", "seg2": "Intermedio", "prop": -37.19716318100149, "lower": -67.45100810486096, "upper": 8.83997201675892, "order": 49}, {"type": "relative", "M": "M2/M1", "seg1": "Hombre", "seg2": "Rural", "prop": -6.411467074209977, "lower": -83.0891044117592, "upper": 420.48471999303814, "order": 50}, {"type": "relative", "M": "M2/M1", "seg1": "Hombre", "seg2": "Total", "prop": -31.30745749675055, "lower": -53.406725527025664, "upper": 3.284436517266372, "order": 51}, {"type": "relative", "M": "M2/M1", "seg1": "Mujer", "seg2": "Urbano", "prop": -47.29555398317858, "lower": -61.4980797872823, "upper": -28.671231209519497, "order": 52}, {"type": "relative", "M": "M2/M1", "seg1": "Mujer", "seg2": "Intermedio", "prop": -26.021468411667392, "lower": -45.44838944008018, "upper": 6.050463925968902, "order": 53}, {"type": "relative", "M": "M2/M1", "seg1": "Mujer", "seg2": "Rural", "prop": -53.537181317810756, "lower": -77.95082611748394, "upper": -4.612421561281495, "order": 54}, {"type": "relative", "M": "M2/M1", "seg1": "Mujer", "seg2": "Total", "prop": -39.815185014441454, "lower": -51.78891955680489, "upper": -25.83234852330902, "order": 55}, {"type": "relative", "M": "M2/M1", "seg1": "Total", "seg2": "Urbano", "prop": -41.93902328439031, "lower": -56.72946066822304, "upper": -19.971891098893355, "order": 56}, {"type": "relative", "M": "M2/M1", "seg1": "Total", "seg2": "Intermedio", "prop": -29.781309223275326, "lower": -48.21135766870921, "upper": -7.85832687647518, "order": 57}, {"type": "relative", "M": "M2/M1", "seg1": "Total", "seg2": "Rural", "prop": -38.80271858467091, "lower": -68.840766239593, "upper": 36.04420213358182, "order": 58}, {"type": "relative", "M": "M2/M1", "seg1": "Total", "seg2": "Total", "prop": -36.986906529837825, "lower": -47.818843598337715, "upper": -23.09092206496171, "order": 59}, {"type": "relative", "M": "M3/M1", "seg1": "Hombre", "seg2": "Urbano", "prop": -19.271341611413263, "lower": -49.413059858142866, "upper": 43.6622626663548, "order": 60}, {"type": "relative", "M": "M3/M1", "seg1": "Hombre", "seg2": "Intermedio", "prop": -29.004253451347832, "lower": -58.21048856373865, "upper": 18.423438086680495, "order": 61}, {"type": "relative", "M": "M3/M1", "seg1": "Hombre", "seg2": "Rural", "prop": 11.390364517597177, "lower": -57.81867512449411, "upper": 202.7826591556841, "order": 62}, {"type": "relative", "M": "M3/M1", "seg1": "Hombre", "seg2": "Total", "prop": -20.146674934681553, "lower": -43.655733128266796, "upper": 14.557301094143085, "order": 63}, {"type": "relative", "M": "M3/M1", "seg1": "Mujer", "seg2": "Urbano", "prop": -16.193159139026733, "lower": -32.95018329528773, "upper": 4.792862430670228, "order": 64}, {"type": "relative", "M": "M3/M1", "seg1": "Mujer", "seg2": "Intermedio", "prop": -9.025227130543746, "lower": -31.010356456624855, "upper": 20.29684335965348, "order": 65}, {"type": "relative", "M": "M3/M1", "seg1": "Mujer", "seg2": "Rural", "prop": -18.916034722588098, "lower": -58.373940824023585, "upper": 46.66827397357671, "order": 66}, {"type": "relative", "M": "M3/M1", "seg1": "Mujer", "seg2": "Total", "prop": -13.741469014370237, "lower": -26.888708512223864, "upper": 2.7947662905966912, "order": 67}, {"type": "relative", "M": "M3/M1", "seg1": "Total", "seg2": "Urbano", "prop": -17.152675071692812, "lower": -34.376393214967536, "upper": 6.599885265845429, "order": 68}, {"type": "relative", "M": "M3/M1", "seg1": "Total", "seg2": "Intermedio", "prop": -16.084351765671837, "lower": -35.38176391597142, "upper": 6.757594876944194, "order": 69}, {"type": "relative", "M": "M3/M1", "seg1": "Total", "seg2": "Rural", "prop": -9.377481277928903, "lower": -45.55476395117299, "upper": 44.32654730429209, "order": 70}, {"type": "relative", "M": "M3/M1", "seg1": "Total", "seg2": "Total", "prop": -15.929893199076467, "lower": -29.36283768312678, "upper": -1.6994432694257413, "order": 71}, {"type": "relative", "M": "M4/M1", "seg1": "Hombre", "seg2": "Urbano", "prop": -31.824325321177465, "lower": -56.861697878226735, "upper": 7.34466339116733, "order": 72}, {"type": "relative", "M": "M4/M1", "seg1": "Hombre", "seg2": "Intermedio", "prop": 3.79821154193408, "lower": -40.99418618805688, "upper": 83.37125140998255, "order": 73}, {"type": "relative", "M": "M4/M1", "seg1": "Hombre", "seg2": "Rural", "prop": -1.6826577874432287, "lower": -64.79889962068009, "upper": 199.7912016930853, "order": 74}, {"type": "relative", "M": "M4/M1", "seg1": "Hombre", "seg2": "Total", "prop": -15.50800897121453, "lower": -39.18291906664654, "upper": 17.138155177818316, "order": 75}, {"type": "relative", "M": "M4/M1", "seg1": "Mujer", "seg2": "Urbano", "prop": -21.969212796769355, "lower": -40.095852307841426, "upper": 0.376270273196823, "order": 76}, {"type": "relative", "M": "M4/M1", "seg1": "Mujer", "seg2": "Intermedio", "prop": -3.20806162530059, "lower": -26.31281894323679, "upper": 29.404314161509443, "order": 77}, {"type": "relative", "M": "M4/M1", "seg1": "Mujer", "seg2": "Rural", "prop": -23.664231819077592, "lower": -58.515132064070606, "upper": 31.800337007915196, "order": 78}, {"type": "relative", "M": "M4/M1", "seg1": "Mujer", "seg2": "Total", "prop": -15.078316249375023, "lower": -28.882746925660534, "upper": -0.6313216487791592, "order": 79}, {"type": "relative", "M": "M4/M1", "seg1": "Total", "seg2": "Urbano", "prop": -25.215802011594135, "lower": -40.626032066077784, "upper": -6.000014090817675, "order": 80}, {"type": "relative", "M": "M4/M1", "seg1": "Total", "seg2": "Intermedio", "prop": -0.966162753819039, "lower": -23.828084600992103, "upper": 30.944446678494725, "order": 81}, {"type": "relative", "M": "M4/M1", "seg1": "Total", "seg2": "Rural", "prop": -16.744235350422933, "lower": -50.733126467861865, "upper": 32.547192959106106, "order": 82}, {"type": "relative", "M": "M4/M1", "seg1": "Total", "seg2": "Total", "prop": -15.197954981646381, "lower": -28.8319383152884, "upper": -0.1091304303785394, "order": 83}, {"type": "relative", "M": "Mz1/M1", "seg1": "Hombre", "seg2": "Urbano", "prop": 945.9206024964838, "lower": 644.5382565067982, "upper": 1343.9250389168774, "order": 84}, {"type": "relative", "M": "Mz1/M1", "seg1": "Hombre", "seg2": "Intermedio", "prop": 1130.0898641849972, "lower": 696.2461746982934, "upper": 1571.8732213377216, "order": 85}, {"type": "relative", "M": "Mz1/M1", "seg1": "Hombre", "seg2": "Rural", "prop": null, "lower": null, "upper": null, "order": 86}, {"type": "relative", "M": "Mz1/M1", "seg1": "Hombre", "seg2": "Total", "prop": 1062.1509152486592, "lower": 827.8537360030283, "upper": 1366.1367232695409, "order": 87}, {"type": "relative", "M": "Mz1/M1", "seg1": "Mujer", "seg2": "Urbano", "prop": 449.8610699065845, "lower": 369.03144717997344, "upper": 548.3087950823204, "order": 88}, {"type": "relative", "M": "Mz1/M1", "seg1": "Mujer", "seg2": "Intermedio", "prop": 473.7101215558037, "lower": 370.6395636054965, "upper": 613.177553473634, "order": 89}, {"type": "relative", "M": "Mz1/M1", "seg1": "Mujer", "seg2": "Rural", "prop": null, "lower": null, "upper": null, "order": 90}, {"type": "relative", "M": "Mz1/M1", "seg1": "Mujer", "seg2": "Total", "prop": 469.84420414970185, "lower": 405.51208862911903, "upper": 539.6562562558718, "order": 91}, {"type": "relative", "M": "Mz1/M1", "seg1": "Total", "seg2": "Urbano", "prop": 619.6068783475642, "lower": 496.8685555744598, "upper": 736.9162524373935, "order": 92}, {"type": "relative", "M": "Mz1/M1", "seg1": "Total", "seg2": "Intermedio", "prop": 697.1344403376258, "lower": 549.4347402212908, "upper": 839.984863387167, "order": 93}, {"type": "relative", "M": "Mz1/M1", "seg1": "Total", "seg2": "Rural", "prop": null, "lower": null, "upper": null, "order": 94}, {"type": "relative", "M": "Mz1/M1", "seg1": "Total", "seg2": "Total", "prop": 669.8723570847277, "lower": 590.9922186794727, "upper": 763.9024965608074, "order": 95}]}}